{
  "roots": ["<rootDir>/src"],
  "transform": {
    "\\.(js|jsx)?$": "babel-jest"
  },
  "testMatch": ["<rootDir>/src/**/?(*.)(test).{js,jsx}"],
  "moduleNameMapper": {
    "\\.(jpg|jpeg|png|gif|eot|otf|webp|svg|ttf|woff|woff2|mp4|webm|wav|mp3|m4a|aac|oga)$": "<rootDir>/__mocks__/fileMocks.js",
    "\\.(css|less|scss|sass)$": "identity-obj-proxy"
  },
  "moduleFileExtensions": ["js", "jsx", "json", "node"],
  "testPathIgnorePatterns": ["/node_modules/", "/public/"],
  "setupFilesAfterEnv": [
    "<rootDir>/setupTests.js"
  ]
}